certbot_dns_infomaniak/__init__.py
certbot_dns_infomaniak/dns_infomaniak.py
certbot_dns_infomaniak/dns_infomaniak_test.py
certbot_dns_infomaniak-0.2.4.dist-info/WHEEL
certbot_dns_infomaniak-0.2.4.dist-info/entry_points.txt
certbot_dns_infomaniak-0.2.4.dist-info/METADATA
certbot_dns_infomaniak-0.2.4.dist-info/RECORD
