Metadata-Version: 2.4
Name: certbot-dns-infomaniak
Version: 0.2.4
Summary: Infomaniak DNS Authenticator plugin for Certbot
Author: Rene Luria
Author-email: Rene Luria <rene.luria@infomaniak.com>
License-Expression: Apache-2.0
Classifier: Development Status :: 3 - Alpha
Classifier: Environment :: Plugins
Classifier: Intended Audience :: System Administrators
Classifier: Operating System :: POSIX :: Linux
Classifier: Programming Language :: Python
Classifier: Programming Language :: Python :: 3.9
Classifier: Programming Language :: Python :: 3.10
Classifier: Programming Language :: Python :: 3.11
Classifier: Programming Language :: Python :: 3.12
Classifier: Programming Language :: Python :: 3.13
Classifier: Programming Language :: Python :: 3.14
Classifier: Topic :: Internet :: WWW/HTTP
Classifier: Topic :: Security
Classifier: Topic :: System :: Installation/Setup
Classifier: Topic :: System :: Networking
Classifier: Topic :: System :: Systems Administration
Classifier: Topic :: Utilities
Requires-Dist: certbot>=0.31.0
Requires-Dist: idna
Requires-Dist: requests
Requires-Dist: requests-mock
Requires-Python: >=3.9
Project-URL: Homepage, https://github.com/infomaniak/certbot-dns-infomaniak
